libnotems/__init__.py
libnotems/libnotems.py
libnotems-1.0.0.dist-info/LICENSE
libnotems-1.0.0.dist-info/METADATA
libnotems-1.0.0.dist-info/WHEEL
libnotems-1.0.0.dist-info/top_level.txt
libnotems-1.0.0.dist-info/RECORD
