Metadata-Version: 2.1
Name: libnotems
Version: 1.0.0
Summary: Note.ms library
Author-email: Ect07 <ect@vivaldi.net>
Project-URL: Homepage, https://github.com/rHanbowChic/Notemon
Project-URL: Issues, https://github.com/rHanbowChic/Notemon/issues
Classifier: Programming Language :: Python :: 3
Classifier: License :: OSI Approved :: MIT License
Classifier: Operating System :: OS Independent
Requires-Python: >=3.8
License-File: LICENSE
Requires-Dist: beautifulsoup4
Requires-Dist: selenium
